LinkShortener.py
LinkShortner.py
__init__.py
prova123.py
test.py
LinkShortener-1.0.1.dist-info/LICENSE
LinkShortener-1.0.1.dist-info/METADATA
LinkShortener-1.0.1.dist-info/WHEEL
LinkShortener-1.0.1.dist-info/top_level.txt
LinkShortener-1.0.1.dist-info/RECORD
