Metadata-Version: 2.1
Name: LinkShortener
Version: 1.0.1
Summary: LinkShortener will automatically shorten links thanks to tinyurl.com.  You can also make links with custom aliases.
Home-page: https://github.com/silviosanto6605/LinkShortener
Author: Silvio Santoriello
Author-email: silviosanto6605@gmail.com
License: MIT
Platform: UNKNOWN
Requires-Dist: requests
Requires-Dist: multipledispatch
Requires-Dist: beautifulsoup4
